easyIntelligence/__init__.py
neuronai-0.0.0.dist-info/LICENSE
neuronai-0.0.0.dist-info/METADATA
neuronai-0.0.0.dist-info/WHEEL
neuronai-0.0.0.dist-info/top_level.txt
neuronai-0.0.0.dist-info/RECORD
